setup.py
findbig/__init__.py
findbig/cli.py
findbig.egg-info/PKG-INFO
findbig.egg-info/SOURCES.txt
findbig.egg-info/dependency_links.txt
findbig.egg-info/entry_points.txt
findbig.egg-info/top_level.txt