Metadata-Version: 1.0
Name: findbig
Version: 0.0.3
Summary: Command-line tool for finding the biggest files in a directory tree
Home-page: http://gitlab.davepedu.com/dave/findbig
Author: dpedu
Author-email: dave@davepedu.com
License: UNKNOWN
Platform: UNKNOWN
